Prism/__init__.py
Prism/_version.py
Prism/data/KEYS/FIELDS
Prism/data/KEYS/FISHATD5.key
Prism/data/KEYS/FISHE1.key
Prism/data/KEYS/FISHE2.key
Prism/data/KEYS/MIX04.key
Prism/data/KEYS/MIX05.key
Prism/data/KEYS/MIX06.key
Prism/data/KEYS/MIX08.key
Prism/data/KEYS/MIX10.key
Prism/data/KEYS/SWCELLP1.key
Prism/data/KEYS/SWCELLP2.key
Prism/data/KEYS/SWPH1.key
Prism/data/KEYS/SWPH2.key
Prism/data/KEYS/SWPH3.key
Prism/data/TRIALS/lan.sessions.f.trn_list
Prism/data/TRIALS/lan.sessions.f.tst_list
Prism/data/TRIALS/lan.sessions.m.trn_list
Prism/data/TRIALS/lan.sessions.m.tst_list
Prism/data/TRIALS/noi.sessions.f.trn_list
Prism/data/TRIALS/noi.sessions.f.tst_list
Prism/data/TRIALS/noi.sessions.m.trn_list
Prism/data/TRIALS/noi.sessions.m.tst_list
Prism/data/TRIALS/rev.sessions.f.trn_list
Prism/data/TRIALS/rev.sessions.f.tst_list
Prism/data/TRIALS/rev.sessions.m.trn_list
Prism/data/TRIALS/rev.sessions.m.tst_list
Prism/data/TRIALS/sch.sessions.f.trn_list
Prism/data/TRIALS/sch.sessions.f.tst_list
Prism/data/TRIALS/sch.sessions.m.trn_list
Prism/data/TRIALS/sch.sessions.m.tst_list
Prism/data/TRIALS/sre10.sessions.f.trn_list
Prism/data/TRIALS/sre10.sessions.f.tst_list
Prism/data/TRIALS/sre10.sessions.m.trn_list
Prism/data/TRIALS/sre10.sessions.m.tst_list
Prism/data/TRIALS/sre108s.sessions.f.trn_list
Prism/data/TRIALS/sre108s.sessions.f.tst_list
Prism/data/TRIALS/sre108s.sessions.m.trn_list
Prism/data/TRIALS/sre108s.sessions.m.tst_list
Prism/data/TRIALS/vel.sessions.f.trn_list
Prism/data/TRIALS/vel.sessions.f.tst_list
Prism/data/TRIALS/vel.sessions.m.trn_list
Prism/data/TRIALS/vel.sessions.m.tst_list
"Prism/data/TRIALS/sre10.conditions/sre10c01,f.keymask"
"Prism/data/TRIALS/sre10.conditions/sre10c01,f.trnids"
"Prism/data/TRIALS/sre10.conditions/sre10c01,f.tstids"
"Prism/data/TRIALS/sre10.conditions/sre10c01,m.keymask"
"Prism/data/TRIALS/sre10.conditions/sre10c01,m.trnids"
"Prism/data/TRIALS/sre10.conditions/sre10c01,m.tstids"
pyannote.db.prism-0.5.dist-info/DESCRIPTION.rst
pyannote.db.prism-0.5.dist-info/entry_points.txt
pyannote.db.prism-0.5.dist-info/METADATA
pyannote.db.prism-0.5.dist-info/metadata.json
pyannote.db.prism-0.5.dist-info/RECORD
pyannote.db.prism-0.5.dist-info/top_level.txt
pyannote.db.prism-0.5.dist-info/WHEEL
