Metadata-Version: 2.0
Name: pyannote.db.prism
Version: 0.5
Summary: Prism plugin for pyannote-database
Home-page: UNKNOWN
Author: Hervé Bredin
Author-email: bredin@limsi.fr
License: UNKNOWN
Platform: UNKNOWN
Classifier: Development Status :: 4 - Beta
Classifier: Intended Audience :: Science/Research
Classifier: License :: OSI Approved :: MIT License
Classifier: Natural Language :: English
Classifier: Programming Language :: Python :: 2
Classifier: Programming Language :: Python :: 2.7
Classifier: Programming Language :: Python :: 3
Classifier: Programming Language :: Python :: 3.4
Classifier: Programming Language :: Python :: 3.5
Classifier: Topic :: Scientific/Engineering
Requires-Dist: pyannote.database (>=0.10.2)
Requires-Dist: pandas (>=0.19)
